README.md
setup.cfg
setup.py
django_404_middleware/__init__.py
django_404_middleware/admin.py
django_404_middleware/apps.py
django_404_middleware/match.py
django_404_middleware/models.py
django_404_middleware/tests.py
django_404_middleware.egg-info/PKG-INFO
django_404_middleware.egg-info/SOURCES.txt
django_404_middleware.egg-info/dependency_links.txt
django_404_middleware.egg-info/top_level.txt
django_404_middleware/migrations/0001_initial.py
django_404_middleware/migrations/0002_ignorable404referer.py
django_404_middleware/migrations/0003_failedurl.py
django_404_middleware/migrations/__init__.py