Metadata-Version: 1.1
Name: django-404-middleware
Version: 0.0.5
Summary: An alternative to Django's BrokenLinkEmailsMiddleware
Home-page: https://github.com/mherrmann/django-404-middleware
Author: Michael Herrmann
Author-email: michael+removethisifyouarehuman@herrmann.io
License: MIT
Keywords: Django 404 Middleware Email
Platform: MacOS
Platform: Windows
Platform: Debian
Platform: Fedora
Platform: CentOS
Platform: Arch
Classifier: Development Status :: 4 - Beta
Classifier: Intended Audience :: Developers
Classifier: License :: OSI Approved :: MIT License
Classifier: Operating System :: OS Independent
Classifier: Programming Language :: Python
Classifier: Programming Language :: Python :: 3
Classifier: Programming Language :: Python :: 3.5
Classifier: Programming Language :: Python :: 3.6
Classifier: Programming Language :: Python :: 3.7
Classifier: Framework :: Django
Classifier: Topic :: Software Development :: Libraries
Classifier: Topic :: Software Development :: Libraries :: Python Modules
